<?xml version="1.0" encoding="UTF-8"?>
<kurzy banka="CNB" datum="27.03.2025" poradi="61">
<tabulka typ="XML_TYP_CNB_KURZY_DEVIZOVEHO_TRHU">
<radek kod="AUD" mena="dolar" mnozstvi="1" kurz="14,605" zeme="Austrálie"/>
<radek kod="BRL" mena="real" mnozstvi="1" kurz="4,019" zeme="Brazílie"/>
<radek kod="BGN" mena="lev" mnozstvi="1" kurz="12,774" zeme="Bulharsko"/>
<radek kod="CNY" mena="žen-min-pi" mnozstvi="1" kurz="3,189" zeme="Čína"/>
<radek kod="DKK" mena="koruna" mnozstvi="1" kurz="3,349" zeme="Dánsko"/>
<radek kod="EUR" mena="euro" mnozstvi="1" kurz="24,985" zeme="EMU"/>
<radek kod="PHP" mena="peso" mnozstvi="100" kurz="40,372" zeme="Filipíny"/>
<radek kod="HKD" mena="dolar" mnozstvi="1" kurz="2,980" zeme="Hongkong"/>
<radek kod="INR" mena="rupie" mnozstvi="100" kurz="27,024" zeme="Indie"/>
<radek kod="IDR" mena="rupie" mnozstvi="1000" kurz="1,399" zeme="Indonesie"/>
<radek kod="ISK" mena="koruna" mnozstvi="100" kurz="17,558" zeme="Island"/>
<radek kod="ILS" mena="nový šekel" mnozstvi="1" kurz="6,308" zeme="Izrael"/>
<radek kod="JPY" mena="jen" mnozstvi="100" kurz="15,361" zeme="Japonsko"/>
<radek kod="ZAR" mena="rand" mnozstvi="1" kurz="1,267" zeme="Jižní Afrika"/>
<radek kod="CAD" mena="dolar" mnozstvi="1" kurz="16,195" zeme="Kanada"/>
<radek kod="KRW" mena="won" mnozstvi="100" kurz="1,581" zeme="Korejská republika"/>
<radek kod="HUF" mena="forint" mnozstvi="100" kurz="6,234" zeme="Maďarsko"/>
<radek kod="MYR" mena="ringgit" mnozstvi="1" kurz="5,228" zeme="Malajsie"/>
<radek kod="MXN" mena="peso" mnozstvi="1" kurz="1,140" zeme="Mexiko"/>
<radek kod="XDR" mena="ZPČ" mnozstvi="1" kurz="30,734" zeme="MMF"/>
<radek kod="NOK" mena="koruna" mnozstvi="1" kurz="2,203" zeme="Norsko"/>
<radek kod="NZD" mena="dolar" mnozstvi="1" kurz="13,299" zeme="Nový Zéland"/>
<radek kod="PLN" mena="zlotý" mnozstvi="1" kurz="5,953" zeme="Polsko"/>
<radek kod="RON" mena="leu" mnozstvi="1" kurz="5,019" zeme="Rumunsko"/>
<radek kod="SGD" mena="dolar" mnozstvi="1" kurz="17,289" zeme="Singapur"/>
<radek kod="SEK" mena="koruna" mnozstvi="1" kurz="2,308" zeme="Švédsko"/>
<radek kod="CHF" mena="frank" mnozstvi="1" kurz="26,235" zeme="Švýcarsko"/>
<radek kod="THB" mena="baht" mnozstvi="100" kurz="68,390" zeme="Thajsko"/>
<radek kod="TRY" mena="lira" mnozstvi="100" kurz="60,957" zeme="Turecko"/>
<radek kod="USD" mena="dolar" mnozstvi="1" kurz="23,170" zeme="USA"/>
<radek kod="GBP" mena="libra" mnozstvi="1" kurz="29,980" zeme="Velká Británie"/>
</tabulka>
</kurzy>
